<?xml version="1.0"?>
<?xml-stylesheet type="text/xsl" href="Portuguese.xsl"?>

<verb>
	<infinitive>ir</infinitive>
	<definition>to go</definition>
	<comments>irregular verb</comments>
	<participles>
		<present>indo</present>
		<past>ido</past>
	</participles>
	<conjugation>
		<mood text="Present Indicative">Present_Indicative</mood>
		<FPS>vou</FPS>
		<SPS>vais</SPS>
		<TPS>vai</TPS>
		<FPP>vamos</FPP>
		<SPP>ides</SPP>
		<TPP>vão</TPP>
	</conjugation>
	<conjugation>
		<mood text="Preterit Indicative">Preterit_Indicative</mood>
		<FPS>fui</FPS>
		<SPS>foste</SPS>
		<TPS>foi</TPS>
		<FPP>fomos</FPP>
		<SPP>fostes</SPP>
		<TPP>foram</TPP>
	</conjugation>
	<conjugation>
		<mood text="Future Indicative">Future_Indicative</mood>
		<FPS>irei</FPS>
		<SPS>irás</SPS>
		<TPS>irá</TPS>
		<FPP>iremos</FPP>
		<SPP>ireis</SPP>
		<TPP>irão</TPP>
	</conjugation>
</verb>
